Fortpy-1.7.7.data/scripts/analyze.py
Fortpy-1.7.7.data/scripts/bestprac.py
Fortpy-1.7.7.data/scripts/compare.py
Fortpy-1.7.7.data/scripts/convert.py
Fortpy-1.7.7.data/scripts/ftypes.py
Fortpy-1.7.7.data/scripts/parse.py
Fortpy-1.7.7.data/scripts/runtests.py
Fortpy-1.7.7.dist-info/DESCRIPTION.rst
Fortpy-1.7.7.dist-info/METADATA
Fortpy-1.7.7.dist-info/RECORD
Fortpy-1.7.7.dist-info/WHEEL
Fortpy-1.7.7.dist-info/metadata.json
Fortpy-1.7.7.dist-info/top_level.txt
fortpy/__init__.py
fortpy/base.py
fortpy/code.py
fortpy/compilers.xml
fortpy/config.py
fortpy/config.xml
fortpy/debug.py
fortpy/docelements.py
fortpy/elements.py
fortpy/msg.py
fortpy/serialize.py
fortpy/settings.py
fortpy/testgen.py
fortpy/tramp.py
fortpy/utility.py
fortpy/interop/__init__.py
fortpy/interop/converter.py
fortpy/interop/ftypes.py
fortpy/interop/make.py
fortpy/isense/__init__.py
fortpy/isense/builtin.py
fortpy/isense/builtin.xml
fortpy/isense/cache.py
fortpy/isense/classes.py
fortpy/isense/completion.py
fortpy/isense/context.py
fortpy/isense/evaluator.py
fortpy/isense/rtupdate.py
fortpy/parsers/__init__.py
fortpy/parsers/docstring.py
fortpy/parsers/executable.py
fortpy/parsers/interface.py
fortpy/parsers/module.py
fortpy/parsers/types.py
fortpy/parsers/variable.py
fortpy/printing/__init__.py
fortpy/printing/docs.py
fortpy/printing/formatting.py
fortpy/scripts/analyze.py
fortpy/scripts/bestprac.py
fortpy/scripts/compare.py
fortpy/scripts/convert.py
fortpy/scripts/ftypes.py
fortpy/scripts/parse.py
fortpy/scripts/runtests.py
fortpy/stats/__init__.py
fortpy/stats/bp.py
fortpy/stats/calltree.py
fortpy/stats/testing.py
fortpy/templates/Makefile.gfortran
fortpy/templates/Makefile.ifort
fortpy/templates/__init__.py
fortpy/templates/float.xml
fortpy/templates/fortpy.f90
fortpy/templates/fpy_auxiliary.f90
fortpy/templates/ftypes.py
fortpy/templates/ftypes_dealloc.f90
fortpy/templates/genf90.py
fortpy/templates/integer.xml
fortpy/templates/static.f90
fortpy/testing/__init__.py
fortpy/testing/automation.py
fortpy/testing/auxiliary.py
fortpy/testing/comparer.py
fortpy/testing/compilers.py
fortpy/testing/elements.py
