Metadata-Version: 2.0
Name: Fortpy
Version: 1.7.7
Summary: Fortran Parsing, Unit Testing and Intellisense
Home-page: https://github.com/rosenbrockc/fortpy
Author: Conrad W Rosenbrock
Author-email: rosenbrockc@gmail.com
License: MIT
Platform: UNKNOWN
Classifier: Development Status :: 5 - Production/Stable
Classifier: Intended Audience :: Developers
Classifier: Natural Language :: English
Classifier: License :: OSI Approved :: MIT License
Classifier: Operating System :: MacOS
Classifier: Programming Language :: Python
Classifier: Programming Language :: Python :: 2
Classifier: Programming Language :: Python :: 2.7
Classifier: Programming Language :: Python :: 3
Classifier: Programming Language :: Python :: 3.4
Classifier: Topic :: Software Development :: Libraries :: Python Modules
Requires-Dist: argparse
Requires-Dist: matplotlib
Requires-Dist: numpy
Requires-Dist: paramiko
Requires-Dist: pyparsing
Requires-Dist: python-dateutil
Requires-Dist: scipy
Requires-Dist: termcolor
Requires-Dist: tqdm
